{
  "trainer_version": 2,
  "args": {
    "data_dir": "../data/backward_run1\\combined",
    "model_dir": "../data/models",
    "epochs": 30,
    "batch_size": 256,
    "lr": 0.0006,
    "weight_decay": 0.0001,
    "optimizer": "adamw",
    "device": "auto",
    "arch": "resnet_s",
    "resume": "../data/models\\backward_best_model.pt",
    "run_name": "backward_st0_iter6",
    "max_samples": 0,
    "scheduler_step": 30,
    "scheduler_gamma": 0.5,
    "eval_interval": 10,
    "policy_temperature": 1.0,
    "val_split": 0.1,
    "split_seed": 2026,
    "split_mode": "sample",
    "min_policy_confidence": 0.0,
    "policy_weight_mode": "none",
    "augment": true,
    "value_mode": "q+z",
    "q_weight": 0.25,
    "seed": 42,
    "grad_clip": 1.0
  },
  "summary": {
    "total_epochs": 30,
    "total_time_s": 99.8,
    "best_val_metric": 2.77119,
    "final_train_loss": 2.76564,
    "param_count": 330619,
    "best_val_policy_acc_top1": 0.3138,
    "best_val_policy_acc_top1_epoch": 20,
    "best_val_policy_acc_top3": 0.6014,
    "best_val_policy_acc_top5": 0.7371
  },
  "metrics_history": [
    {
      "epoch": 1,
      "train_loss": 3.13632,
      "train_policy_loss": 2.59999,
      "train_value_loss": 0.53633,
      "lr": 0.0006,
      "epoch_time_s": 5.5,
      "train_policy_acc_top1": 0.3145,
      "train_policy_acc_top3": 0.5899,
      "train_policy_acc_top5": 0.7142,
      "train_value_mae": 0.6444,
      "train_value_sign_acc": 0.6365,
      "val_loss": 3.0957,
      "val_policy_loss": 2.57141,
      "val_value_loss": 0.52429,
      "val_policy_acc_top1": 0.3079,
      "val_policy_acc_top3": 0.6014,
      "val_policy_acc_top5": 0.7201,
      "val_value_mae": 0.6645,
      "val_value_sign_acc": 0.6268,
      "kl_divergence": 2.310669
    },
    {
      "epoch": 2,
      "train_loss": 3.0439,
      "train_policy_loss": 2.56477,
      "train_value_loss": 0.47913,
      "lr": 0.0006,
      "epoch_time_s": 2.9
    },
    {
      "epoch": 3,
      "train_loss": 3.0191,
      "train_policy_loss": 2.55528,
      "train_value_loss": 0.46382,
      "lr": 0.0006,
      "epoch_time_s": 2.9
    },
    {
      "epoch": 4,
      "train_loss": 2.9879,
      "train_policy_loss": 2.54085,
      "train_value_loss": 0.44704,
      "lr": 0.0006,
      "epoch_time_s": 2.7
    },
    {
      "epoch": 5,
      "train_loss": 2.97611,
      "train_policy_loss": 2.54353,
      "train_value_loss": 0.43257,
      "lr": 0.0006,
      "epoch_time_s": 2.9
    },
    {
      "epoch": 6,
      "train_loss": 2.95913,
      "train_policy_loss": 2.5346,
      "train_value_loss": 0.42453,
      "lr": 0.0006,
      "epoch_time_s": 2.7
    },
    {
      "epoch": 7,
      "train_loss": 2.95087,
      "train_policy_loss": 2.52972,
      "train_value_loss": 0.42115,
      "lr": 0.0006,
      "epoch_time_s": 2.8
    },
    {
      "epoch": 8,
      "train_loss": 2.931,
      "train_policy_loss": 2.53116,
      "train_value_loss": 0.39984,
      "lr": 0.0006,
      "epoch_time_s": 2.8
    },
    {
      "epoch": 9,
      "train_loss": 2.92795,
      "train_policy_loss": 2.52965,
      "train_value_loss": 0.3983,
      "lr": 0.0006,
      "epoch_time_s": 2.8
    },
    {
      "epoch": 10,
      "train_loss": 2.92354,
      "train_policy_loss": 2.5243,
      "train_value_loss": 0.39924,
      "lr": 0.0006,
      "epoch_time_s": 3.0,
      "train_policy_acc_top1": 0.3347,
      "train_policy_acc_top3": 0.6216,
      "train_policy_acc_top5": 0.7415,
      "train_value_mae": 0.5357,
      "train_value_sign_acc": 0.7165,
      "val_loss": 2.98375,
      "val_policy_loss": 2.55269,
      "val_value_loss": 0.43107,
      "val_policy_acc_top1": 0.313,
      "val_policy_acc_top3": 0.598,
      "val_policy_acc_top5": 0.7201,
      "val_value_mae": 0.567,
      "val_value_sign_acc": 0.7023,
      "kl_divergence": 2.361837
    },
    {
      "epoch": 11,
      "train_loss": 2.90593,
      "train_policy_loss": 2.51668,
      "train_value_loss": 0.38925,
      "lr": 0.0006,
      "epoch_time_s": 2.8
    },
    {
      "epoch": 12,
      "train_loss": 2.88778,
      "train_policy_loss": 2.50938,
      "train_value_loss": 0.3784,
      "lr": 0.0006,
      "epoch_time_s": 2.8
    },
    {
      "epoch": 13,
      "train_loss": 2.8791,
      "train_policy_loss": 2.50847,
      "train_value_loss": 0.37063,
      "lr": 0.0006,
      "epoch_time_s": 3.1
    },
    {
      "epoch": 14,
      "train_loss": 2.87102,
      "train_policy_loss": 2.50574,
      "train_value_loss": 0.36528,
      "lr": 0.0006,
      "epoch_time_s": 2.8
    },
    {
      "epoch": 15,
      "train_loss": 2.86302,
      "train_policy_loss": 2.50471,
      "train_value_loss": 0.35831,
      "lr": 0.0006,
      "epoch_time_s": 2.8
    },
    {
      "epoch": 16,
      "train_loss": 2.85259,
      "train_policy_loss": 2.5004,
      "train_value_loss": 0.35219,
      "lr": 0.0006,
      "epoch_time_s": 2.8
    },
    {
      "epoch": 17,
      "train_loss": 2.85321,
      "train_policy_loss": 2.50114,
      "train_value_loss": 0.35207,
      "lr": 0.0006,
      "epoch_time_s": 2.8
    },
    {
      "epoch": 18,
      "train_loss": 2.84233,
      "train_policy_loss": 2.49792,
      "train_value_loss": 0.34441,
      "lr": 0.0006,
      "epoch_time_s": 2.9
    },
    {
      "epoch": 19,
      "train_loss": 2.83757,
      "train_policy_loss": 2.49048,
      "train_value_loss": 0.34709,
      "lr": 0.0006,
      "epoch_time_s": 2.9
    },
    {
      "epoch": 20,
      "train_loss": 2.82496,
      "train_policy_loss": 2.49023,
      "train_value_loss": 0.33473,
      "lr": 0.0006,
      "epoch_time_s": 3.1,
      "train_policy_acc_top1": 0.3354,
      "train_policy_acc_top3": 0.621,
      "train_policy_acc_top5": 0.7433,
      "train_value_mae": 0.47,
      "train_value_sign_acc": 0.7726,
      "val_loss": 2.96535,
      "val_policy_loss": 2.56745,
      "val_value_loss": 0.3979,
      "val_policy_acc_top1": 0.3138,
      "val_policy_acc_top3": 0.5818,
      "val_policy_acc_top5": 0.7193,
      "val_value_mae": 0.5176,
      "val_value_sign_acc": 0.7362,
      "kl_divergence": 2.342648
    },
    {
      "epoch": 21,
      "train_loss": 2.80997,
      "train_policy_loss": 2.48367,
      "train_value_loss": 0.32629,
      "lr": 0.0006,
      "epoch_time_s": 2.8
    },
    {
      "epoch": 22,
      "train_loss": 2.81461,
      "train_policy_loss": 2.48746,
      "train_value_loss": 0.32715,
      "lr": 0.0006,
      "epoch_time_s": 3.0
    },
    {
      "epoch": 23,
      "train_loss": 2.81135,
      "train_policy_loss": 2.48643,
      "train_value_loss": 0.32492,
      "lr": 0.0006,
      "epoch_time_s": 2.9
    },
    {
      "epoch": 24,
      "train_loss": 2.8055,
      "train_policy_loss": 2.48698,
      "train_value_loss": 0.31852,
      "lr": 0.0006,
      "epoch_time_s": 2.8
    },
    {
      "epoch": 25,
      "train_loss": 2.79514,
      "train_policy_loss": 2.48373,
      "train_value_loss": 0.31141,
      "lr": 0.0006,
      "epoch_time_s": 2.5
    },
    {
      "epoch": 26,
      "train_loss": 2.78697,
      "train_policy_loss": 2.47829,
      "train_value_loss": 0.30868,
      "lr": 0.0006,
      "epoch_time_s": 2.5
    },
    {
      "epoch": 27,
      "train_loss": 2.7951,
      "train_policy_loss": 2.47988,
      "train_value_loss": 0.31522,
      "lr": 0.0006,
      "epoch_time_s": 2.8
    },
    {
      "epoch": 28,
      "train_loss": 2.77406,
      "train_policy_loss": 2.47438,
      "train_value_loss": 0.29968,
      "lr": 0.0006,
      "epoch_time_s": 2.6
    },
    {
      "epoch": 29,
      "train_loss": 2.77119,
      "train_policy_loss": 2.47337,
      "train_value_loss": 0.29782,
      "lr": 0.0006,
      "epoch_time_s": 2.9
    },
    {
      "epoch": 30,
      "train_loss": 2.76564,
      "train_policy_loss": 2.46994,
      "train_value_loss": 0.2957,
      "lr": 0.0003,
      "epoch_time_s": 3.0,
      "train_policy_acc_top1": 0.3551,
      "train_policy_acc_top3": 0.6494,
      "train_policy_acc_top5": 0.7703,
      "train_value_mae": 0.4272,
      "train_value_sign_acc": 0.7993,
      "val_loss": 2.94945,
      "val_policy_loss": 2.56495,
      "val_value_loss": 0.3845,
      "val_policy_acc_top1": 0.2935,
      "val_policy_acc_top3": 0.5861,
      "val_policy_acc_top5": 0.7371,
      "val_value_mae": 0.4986,
      "val_value_sign_acc": 0.732,
      "kl_divergence": 2.295753
    }
  ]
}